aldera/__init__.py
aldera/app.py
aldera/config.py
aldera/mail/__init__.py
aldera/mail/flask_mail.py
aldera/mail/backends/__init__.py
aldera/mail/backends/aws.py
aldera/sms/__init__.py
aldera/sms/flask_sms.py
aldera/sms/backends/__init__.py
aldera/sms/backends/async_aws.py
aldera/sms/backends/aws.py
aldera/sms/backends/locmem.py
aldera-1.0.3.dist-info/METADATA
aldera-1.0.3.dist-info/WHEEL
aldera-1.0.3.dist-info/licenses/LICENSE
aldera-1.0.3.dist-info/RECORD
