Metadata-Version: 2.4
Name: aldera
Version: 1.0.3
Summary: A lightweight Python library for sending email and SMS messages using AWS.
Project-URL: Homepage, https://github.com/zack-young-ideas/aldera-python
Project-URL: Documentation, https://github.com/zack-young-ideas/aldera-python/wiki
Project-URL: Repository, https://github.com/zack-young-ideas/aldera-python
Author-email: Zack Young <zackyoung8709@gmail.com>
License:                                  Apache License
License-File: LICENSE
Keywords: AWS,Django,SMS,SNS,async,cloud,deployment
Classifier: Framework :: Django
Classifier: Intended Audience :: Developers
Classifier: Operating System :: OS Independent
Classifier: Programming Language :: Python :: 3
Classifier: Programming Language :: Python :: 3 :: Only
Classifier: Programming Language :: Python :: 3.10
Classifier: Programming Language :: Python :: 3.11
Classifier: Programming Language :: Python :: 3.12
Requires-Python: >=3.10
Requires-Dist: boto3>=1.34.0
Requires-Dist: botocore>=1.34.0
Provides-Extra: async
Requires-Dist: aioboto3>=12.0.0; extra == 'async'
